projectoxford/__init__.py
projectoxford-1.0.1.dist-info/METADATA
projectoxford-1.0.1.dist-info/NOTICE.rst
projectoxford-1.0.1.dist-info/WHEEL
projectoxford-1.0.1.dist-info/top_level.txt
projectoxford-1.0.1.dist-info/RECORD
