Metadata-Version: 2.1
Name: projectoxford
Version: 1.0.1
Summary: Deprecated Project Oxford SDK. Install `projectoxford<1` for legacy versions.
Home-page: https://docs.microsoft.com/python/api/overview/azure/cognitive-services
Author: Microsoft Corporation
Author-email: python@microsoft.com
License: UNKNOWN
Platform: UNKNOWN
License-File: NOTICE.rst
